MANIFEST.in
requirements.txt
setup.cfg
setup.py
vine_python.egg-info/PKG-INFO
vine_python.egg-info/SOURCES.txt
vine_python.egg-info/dependency_links.txt
vine_python.egg-info/requires.txt
vine_python.egg-info/top_level.txt
vineapi/__init__.py
vineapi/api.py
vineapi/exceptions.py