Metadata-Version: 1.1
Name: vine-python
Version: 1.0.5
Summary: Python Vine API
Home-page: https://github.com/rohitkhatri/vine-python
Author: Rohit Khatri
Author-email: developer.rohitkhatri@gmail.com
License: MIT
Keywords: vine api python sdk
Platform: UNKNOWN
Classifier: Development Status :: 4 - Beta
Classifier: Intended Audience :: Developers
Classifier: Operating System :: OS Independent
Classifier: Programming Language :: Python :: 3.5
Classifier: Operating System :: OS Independent
Classifier: Topic :: Software Development :: Libraries :: Python Modules
